README.rst
setup.py
pyShortUrl.egg-info/PKG-INFO
pyShortUrl.egg-info/SOURCES.txt
pyShortUrl.egg-info/dependency_links.txt
pyShortUrl.egg-info/requires.txt
pyShortUrl.egg-info/top_level.txt
pyshorturl/__init__.py
pyshorturl/conf.py
pyshorturl/providers/__init__.py
pyshorturl/providers/base.py
pyshorturl/providers/bit_ly.py
pyshorturl/providers/bit_ly_v2.py
pyshorturl/providers/gimme_bar.py
pyshorturl/providers/git_io.py
pyshorturl/providers/goo_gl.py
pyshorturl/providers/is_gd.py
pyshorturl/providers/tinyurl_com.py
pyshorturl/providers/v_gd.py