Metadata-Version: 1.1
Name: pyShortUrl
Version: 0.9.3
Summary: A python library to shorten urls using one of the url shortening services
Home-page: https://github.com/fictivekin/pyshorturl
Author: Fictive Kin (mostly of previous work by Parth Bhatt)
Author-email: systems@fictivekin.com
License: MIT
Keywords: url shortening qrcode qr goo.gl bit.ly tinyurl.com j.mp bitly.com v.gd is.gd
Platform: Linux
Platform: Max OS X
Platform: Windows
Platform: BSD
Platform: Unix
Classifier: Development Status :: 4 - Beta
Classifier: Environment :: Console
Classifier: Intended Audience :: Developers
Classifier: Intended Audience :: End Users/Desktop
Classifier: Intended Audience :: Other Audience
Classifier: License :: OSI Approved :: MIT License
Classifier: Operating System :: OS Independent
Classifier: Programming Language :: Python
Classifier: Topic :: Communications
Classifier: Topic :: Internet :: WWW/HTTP
Classifier: Topic :: Software Development :: Libraries :: Python Modules
Classifier: Topic :: Utilities
